parble/__init__.py
parble/_version.py
parble/client.py
parble/commands.py
parble/exceptions.py
parble/models.py
parble/sdk.py
parble/session.py
parble/settings.py
parble/utils.py
parble/resources/__init__.py
parble/resources/base.py
parble/resources/files.py
parble-0.4.1.dist-info/METADATA
parble-0.4.1.dist-info/WHEEL
parble-0.4.1.dist-info/entry_points.txt
parble-0.4.1.dist-info/licenses/LICENSE
parble-0.4.1.dist-info/RECORD
